{
    "Presidential debates": [
        {
            "Title": "We are reporters from five newsrooms covering the 2024 election results. Ask us anything. \n",
            "Score": 50,
            "URL": "https://www.reddit.com/r/politics/comments/1gl1w0a/we_are_reporters_from_five_newsrooms_covering_the/",
            "Created_UTC": 1730908979.0
        },
        {
            "Title": "Why we need age limits for presidential candidates",
            "Score": 199,
            "URL": "https://www.washingtonpost.com/opinions/2024/10/18/biden-trump-president-age-limit/",
            "Created_UTC": 1729253320.0
        },
        {
            "Title": "Vice Presidential Debate Draws 39 Million on Eight TV Networks",
            "Score": 33,
            "URL": "https://www.bloomberg.com/news/articles/2024-10-02/vice-presidential-debate-draws-39-million-on-eight-tv-networks?cmpid%3D=socialflow-twitter-politics&utm_medium=social&utm_content=politics&utm_source=twitter&utm_campaign=socialflow-organic&embedded-checkout=true",
            "Created_UTC": 1727897647.0
        },
        {
            "Title": "Fact-checking the vice-presidential debate between Vance and Walz",
            "Score": 107,
            "URL": "https://www.washingtonpost.com/politics/2024/10/02/fact-check-vp-debate-vance-walz/",
            "Created_UTC": 1727874072.0
        },
        {
            "Title": "NPR fact checked the Vance-Walz vice presidential debate. Here\u2019s what we found",
            "Score": 5291,
            "URL": "https://www.npr.org/2024/10/02/nx-s1-5135675/jd-vance-tim-walz-vp-debate-fact-check",
            "Created_UTC": 1727871843.0
        },
        {
            "Title": "Top Foreign-Policy Takeaways From the Vice Presidential Debate",
            "Score": 6,
            "URL": "https://foreignpolicy.com/2024/10/02/walz-vance-vp-debate-top-foreign-policy-takeaways/",
            "Created_UTC": 1727876110.0
        },
        {
            "Title": "Discussion Thread: 2024 Vice Presidential Debate Between Senator J.D. Vance and Governor Tim Walz, Part 4 (Post-Debate Thread)",
            "Score": 582,
            "URL": "https://www.reddit.com/r/politics/comments/1fu699x/discussion_thread_2024_vice_presidential_debate/",
            "Created_UTC": 1727837327.0
        },
        {
            "Title": "Education a potential flashpoint in Vance-Walz vice presidential debate",
            "Score": 69,
            "URL": "https://thehill.com/homenews/education/4907669-vance-walz-vice-presidential-debate-education/",
            "Created_UTC": 1727805369.0
        },
        {
            "Title": "Discussion Thread: 2024 Vice Presidential Debate Between Senator J.D. Vance and Governor Tim Walz",
            "Score": 3819,
            "URL": "https://www.reddit.com/r/politics/comments/1fu1ndk/discussion_thread_2024_vice_presidential_debate/",
            "Created_UTC": 1727823448.0
        },
        {
            "Title": "Discussion Thread: 2024 Vice Presidential Debate Between Senator J.D. Vance and Governor Tim Walz, Part 2",
            "Score": 6621,
            "URL": "https://www.reddit.com/r/politics/comments/1fu4xi6/discussion_thread_2024_vice_presidential_debate/",
            "Created_UTC": 1727833153.0
        },
        {
            "Title": "Discussion Thread: 2024 Vice Presidential Debate Between Senator J.D. Vance and Governor Tim Walz, Part 3",
            "Score": 518,
            "URL": "https://www.reddit.com/r/politics/comments/1fu5w1x/discussion_thread_2024_vice_presidential_debate/",
            "Created_UTC": 1727836163.0
        },
        {
            "Title": "Walz and Vance will meet in their first and possibly only vice presidential debate",
            "Score": 102,
            "URL": "https://apnews.com/article/vance-walz-vice-presidential-debate-election-66ff2e5e45a8dda55b0a2242fc238fdc",
            "Created_UTC": 1727757653.0
        },
        {
            "Title": "Why Tuesday\u2019s vice presidential debate could matter more than history suggests",
            "Score": 84,
            "URL": "https://apnews.com/article/vice-presidential-debate-walz-vance-explainer-campaign-918bc02012b4ec00c3b283fa40f654cd",
            "Created_UTC": 1727700555.0
        },
        {
            "Title": "Numbers show Vance-Walz vice-presidential debate could change the course of the election",
            "Score": 215,
            "URL": "https://www.independent.co.uk/news/world/americas/us-politics/vp-debate-vance-walz-poll-b2620177.html",
            "Created_UTC": 1727622955.0
        },
        {
            "Title": "Vance says Republicans need 'to do so much better of a job' winning back 'trust' on abortion",
            "Score": 58,
            "URL": "https://www.nbcnews.com/politics/jd-vance/vance-republicans-much-better-job-winning-back-trust-abortion-rcna173566",
            "Created_UTC": 1727838806.0
        },
        {
            "Title": "Vance-Walz VP debate going to be \u2018most important \u2026 in US history\u2019: Presidential historian",
            "Score": 106,
            "URL": "https://thehill.com/homenews/media/4896026-vance-walz-vp-debate-cbs-trump-harris/",
            "Created_UTC": 1727214468.0
        },
        {
            "Title": "Tim Ryan to Tim Walz: \u2018Be yourself\u2019 at vice presidential debate",
            "Score": 113,
            "URL": "https://thehill.com/homenews/campaign/4892896-ohio-democrat-tells-walz-to-be-yourself-ahead-of-vp-debate/",
            "Created_UTC": 1727025121.0
        },
        {
            "Title": "Harris accepts CNN offer for 2nd presidential debate on Oct. 23",
            "Score": 351,
            "URL": "https://abcnews.go.com/Politics/harris-accepts-cnn-offer-2nd-presidential-debate-oct/story?id=113899130",
            "Created_UTC": 1726940874.0
        },
        {
            "Title": "Polls show Harris gaining after the presidential debate",
            "Score": 799,
            "URL": "https://abcnews.go.com/538/polls-show-harris-gaining-after-presidential-debate/story?id=113745432",
            "Created_UTC": 1726602507.0
        },
        {
            "Title": "Trump Rules Out More Presidential Debates With Harris",
            "Score": 95,
            "URL": "https://www.bloomberg.com/news/articles/2024-09-12/trump-rules-out-more-presidential-debates-with-harris",
            "Created_UTC": 1726170055.0
        },
        {
            "Title": "Harris Extends Lead Over Trump After First Presidential Debate",
            "Score": 2410,
            "URL": "https://pro.morningconsult.com/instant-intel/harris-trump-first-debate-poll",
            "Created_UTC": 1726164852.0
        },
        {
            "Title": "Early polls say Harris won the presidential debate",
            "Score": 315,
            "URL": "https://abcnews.go.com/538/early-polls-harris-won-presidential-debate/story?id=113590484",
            "Created_UTC": 1726135257.0
        },
        {
            "Title": "Gov. Tim Walz visits Arizona ahead of presidential debate",
            "Score": 268,
            "URL": "https://www.statepress.com/article/2024/09/tim-walz-arizona-visit",
            "Created_UTC": 1726118333.0
        },
        {
            "Title": "2024 presidential debate was an 'eye opener' in suburban Philadelphia",
            "Score": 186,
            "URL": "https://www.fox29.com/news/2024-presidential-debate-was-eye-opener-suburban-philadelphia",
            "Created_UTC": 1726156119.0
        },
        {
            "Title": "Trump says there won\u2019t be a third presidential debate",
            "Score": 62,
            "URL": "https://www.cnn.com/2024/09/12/politics/donald-trump-no-third-debate/index.html",
            "Created_UTC": 1726171893.0
        },
        {
            "Title": "Trump says there won\u2019t be a third presidential debate\n",
            "Score": 31,
            "URL": "https://edition.cnn.com/2024/09/12/politics/donald-trump-no-third-debate/index.html",
            "Created_UTC": 1726170835.0
        },
        {
            "Title": "Harris campaign wants an October presidential debate, spokesperson says",
            "Score": 351,
            "URL": "https://www.reuters.com/world/us/harris-campaign-wants-an-october-presidential-debate-spokesperson-says-2024-09-11/",
            "Created_UTC": 1726078747.0
        },
        {
            "Title": "Harris campaign calls for 2nd presidential debate, challenging Trump",
            "Score": 1488,
            "URL": "https://abcnews.go.com/Politics/harris-campaign-calls-2nd-presidential-debate-challenging-trump/story?id=113574226",
            "Created_UTC": 1726050963.0
        },
        {
            "Title": "Harris campaign wants a second presidential debate with Trump",
            "Score": 4920,
            "URL": "https://www.washingtonpost.com/politics/2024/09/10/harris-campaign-wants-second-presidential-debate-with-trump/",
            "Created_UTC": 1726023688.0
        },
        {
            "Title": "Swing state voters respond to the presidential debate: \u2018Trump couldn\u2019t even look at her!\u2019",
            "Score": 1421,
            "URL": "https://www.theguardian.com/us-news/2024/sep/12/swing-state-voters-debate-reaction?CMP=Share_AndroidApp_Other",
            "Created_UTC": 1726155875.0
        },
        {
            "Title": "Fact-checking the ABC News presidential debate",
            "Score": 7,
            "URL": "https://amp.cnn.com/cnn/2024/09/10/politics/fact-check-debate-trump-harris",
            "Created_UTC": 1726037497.0
        },
        {
            "Title": "DC mayor responds to Trump's Capitol riot blame during presidential debate with Harris",
            "Score": 91,
            "URL": "https://wjla.com/news/local/trump-harris-capitol-riots-dc-mayor-muriel-bowser-debate-presidential-january-6-stop-the-steal-deny-national-guard-claims-rioters-insurrection-metropolitan-police-donald-kamala-president-vice",
            "Created_UTC": 1726159847.0
        },
        {
            "Title": "This Donald Trump Stock Market Sentiment Indicator Signals He Lost The Presidential Debate",
            "Score": 151,
            "URL": "https://www.investors.com/news/donald-trump-stock-djt-presidential-debate-kamala-harris/",
            "Created_UTC": 1726149293.0
        },
        {
            "Title": "9 Body Language Tells From the Presidential Debate",
            "Score": 30,
            "URL": "https://www.politico.com/news/magazine/2024/09/11/body-language-presidential-debate-harris-trump-00178569",
            "Created_UTC": 1726033563.0
        },
        {
            "Title": "Haitian immigrants fueled Springfield's growth, and now a presidential debate",
            "Score": 39,
            "URL": "https://www.reuters.com/world/us/haitian-immigrants-fueled-springfields-growth-now-us-presidential-debate-2024-09-11/",
            "Created_UTC": 1726077687.0
        },
        {
            "Title": "5 key takeaways from the first Harris-Trump presidential debate",
            "Score": 172,
            "URL": "https://www.nbcnews.com/politics/2024-election/presidential-debate-takeaways-trump-harris-rcna169060",
            "Created_UTC": 1726022757.0
        },
        {
            "Title": "Fact checking debate claims from Trump and Harris' 2024 presidential faceoff",
            "Score": 24,
            "URL": "https://www.cbsnews.com/news/trump-harris-abc-debate-fact-check/",
            "Created_UTC": 1726076484.0
        },
        {
            "Title": "Trump calls Jan. 6 rioters 'we' in discussing insurrection at presidential debate",
            "Score": 1196,
            "URL": "https://www.usatoday.com/story/news/politics/elections/2024/09/10/trump-calls-jan-6-rioters-we-presidential-debate/75167915007/",
            "Created_UTC": 1726024695.0
        },
        {
            "Title": "Trump Throws JD Vance Under the Bus On Abortion During Presidential Debate",
            "Score": 1014,
            "URL": "https://www.thedailybeast.com/trump-throws-jd-vance-under-the-bus-on-abortion-during-presidential-debate",
            "Created_UTC": 1726022507.0
        },
        {
            "Title": "Fact-checking Kamala Harris and Donald Trump's 1st presidential debate",
            "Score": 52,
            "URL": "https://abcnews.go.com/Politics/fact-checking-kamala-harris-donald-trumps-1st-presidential/story?id=113567997",
            "Created_UTC": 1726024887.0
        },
        {
            "Title": "Harris toys with Trump in U.S. presidential debate | In starkly different contest from earlier Biden debate, she knocks him off-topic",
            "Score": 184,
            "URL": "https://www.cbc.ca/news/world/debate-harris-trump-2024-analysis-1.7319309",
            "Created_UTC": 1726071135.0
        },
        {
            "Title": "Ukrainians Will Also Be Watching Tonight\u2019s Presidential Debate Anxiously",
            "Score": 123,
            "URL": "https://www.thenation.com/article/world/trump-harris-debate-ukraine/",
            "Created_UTC": 1725979799.0
        },
        {
            "Title": "US presidential debate highlights: Harris riled Trump on abortion, economy and foreign policy",
            "Score": 46,
            "URL": "https://www.reuters.com/world/us/elections/us-presidential-debate-live-kamala-harris-vs-donald-trump-2024-09-10/",
            "Created_UTC": 1726077873.0
        },
        {
            "Title": "Trump shares anti-Haitian immigrant cat memes ahead of first presidential debate",
            "Score": 225,
            "URL": "https://www.salon.com/2024/09/10/shares-anti-haitian-cat-memes-ahead-of-first-presidential-debate/",
            "Created_UTC": 1726015519.0
        },
        {
            "Title": "Trump, GOP fuel conspiracy theories: Eating pets, a rigged debate and QAnon Led by their presidential nominee, Republicans have increasingly embraced false tales and groundless claims once relegated to the political fringes. Some in the party are worried.",
            "Score": 590,
            "URL": "https://www.washingtonpost.com/politics/2024/09/15/trump-republicans-baseless-conspiracy-theories/",
            "Created_UTC": 1726446087.0
        },
        {
            "Title": "Kamala Harris Says Donald Trump Is \u2018Gonna Lie\u2019 at Presidential Debate",
            "Score": 11631,
            "URL": "https://www.thedailybeast.com/kamala-harris-says-donald-trump-is-gonna-lie-at-presidential-debate",
            "Created_UTC": 1725904645.0
        },
        {
            "Title": "NPR fact checked the Harris-Trump presidential debate. Here's what we found",
            "Score": 71,
            "URL": "https://www.npr.org/2024/09/11/g-s1-21932/fact-check-trump-harris-presidential-debate-2024",
            "Created_UTC": 1726033748.0
        },
        {
            "Title": "Snap poll after debate reveals state of presidential race between Trump and Harris",
            "Score": 28,
            "URL": "https://www.independent.co.uk/news/world/americas/us-politics/kamala-harris-debate-donald-trump-poll-who-won-b2610700.html",
            "Created_UTC": 1726065527.0
        },
        {
            "Title": "Where is the the presidential debate being held? Inside historic venue",
            "Score": 29,
            "URL": "https://www.usatoday.com/story/news/nation/2024/09/09/presidential-debate-harris-trump-2024-venue/75057068007/",
            "Created_UTC": 1726009441.0
        },
        {
            "Title": "Discussion Thread: First Presidential Debate of the 2024 General Election Between Vice President Kamala Harris and Former President Donald Trump, Part 7 (Post-Debate Thread)",
            "Score": 2264,
            "URL": "https://www.reddit.com/r/politics/comments/1fdzwy5/discussion_thread_first_presidential_debate_of/",
            "Created_UTC": 1726022751.0
        },
        {
            "Title": "Discussion Thread: First Presidential Debate of the 2024 General Election Between Vice President Kamala Harris and Former President Donald Trump, Part 6 (Post-Debate Thread)",
            "Score": 2139,
            "URL": "https://www.reddit.com/r/politics/comments/1fdzlp3/discussion_thread_first_presidential_debate_of/",
            "Created_UTC": 1726021757.0
        },
        {
            "Title": "Taylor Swift endorses Kamala Harris minutes after presidential debate: \u2018I\u2019ve made my choice\u2019",
            "Score": 344,
            "URL": "https://nypost.com/2024/09/10/us-news/taylor-swift-endorses-kamala-harris-minutes-after-presidential-debate-ive-made-my-choice/",
            "Created_UTC": 1726025301.0
        },
        {
            "Title": "Taylor Swift endorses Kamala Harris after presidential debate: \u2018She fights for the rights and causes I believe\u2019",
            "Score": 9981,
            "URL": "https://www.independent.co.uk/news/world/americas/us-politics/taylor-swift-harris-endorsement-presidential-election-b2610609.html",
            "Created_UTC": 1726024223.0
        },
        {
            "Title": "Here are the rules for tonight's presidential debate between Trump and Harris",
            "Score": 133,
            "URL": "https://www.cbsnews.com/news/trump-harris-debate-rules-2024/",
            "Created_UTC": 1725969389.0
        },
        {
            "Title": "Who spoke the most - and the least - in the US Presidential debate.",
            "Score": 63,
            "URL": "https://www.cnn.com/2024/09/10/politics/speaking-times-harris-trump-debate-dg/index.html",
            "Created_UTC": 1726023934.0
        },
        {
            "Title": "Trump, Biden and Harris Make Rare Joint Appearance at 9/11 Memorial Hours After Presidential Debate.",
            "Score": 101,
            "URL": "https://people.com/trump-biden-harris-rare-joint-appearance-9-11-memorial-8710114",
            "Created_UTC": 1726061006.0
        },
        {
            "Title": "David Muir, known for his \"apolitical image,\" to moderate Trump-Harris presidential debate tonight",
            "Score": 115,
            "URL": "https://www.syracuse.com/news/2024/09/syracuse-native-david-muir-to-moderate-trump-harris-presidential-debate-tonight.html",
            "Created_UTC": 1725973140.0
        },
        {
            "Title": "Harris says Trump \u2018sold us out on China\u2019: Highlights from the presidential debate on trade and tariffs",
            "Score": 128,
            "URL": "https://www.cnbc.com/2024/09/11/harris-vs-trump-on-china-debate-highlights-on-trade-and-tariffs.html",
            "Created_UTC": 1726031112.0
        },
        {
            "Title": "Tonight\u2019s presidential debate will be streamed on Disney+ and Hulu for the first time ever.",
            "Score": 368,
            "URL": "https://www.hollywoodreporter.com/tv/tv-news/watch-stream-harris-trump-presidential-debate-online-free-1235995804/",
            "Created_UTC": 1725980312.0
        },
        {
            "Title": "Harris and Trump make final preparations ahead of crucial presidential debate in Philadelphia",
            "Score": 28,
            "URL": "https://www.theguardian.com/us-news/article/2024/sep/10/harris-and-trump-make-final-preparations-ahead-of-crucial-presidential-debate-in-philadelphia",
            "Created_UTC": 1725955153.0
        },
        {
            "Title": "Discussion Thread: First Presidential Debate of the 2024 General Election Between Vice President Kamala Harris and Former President Donald Trump",
            "Score": 4766,
            "URL": "https://www.reddit.com/r/politics/comments/1fdtubw/discussion_thread_first_presidential_debate_of/",
            "Created_UTC": 1726004756.0
        },
        {
            "Title": "Discussion Thread: First Presidential Debate of the 2024 General Election Between Vice President Kamala Harris and Former President Donald Trump, Part 2",
            "Score": 15602,
            "URL": "https://www.reddit.com/r/politics/comments/1fdy9k3/discussion_thread_first_presidential_debate_of/",
            "Created_UTC": 1726017426.0
        },
        {
            "Title": "Discussion Thread: First Presidential Debate of the 2024 General Election Between Vice President Kamala Harris and Former President Donald Trump, Part 5",
            "Score": 7065,
            "URL": "https://www.reddit.com/r/politics/comments/1fdz7kl/discussion_thread_first_presidential_debate_of/",
            "Created_UTC": 1726020514.0
        },
        {
            "Title": "Discussion Thread: First Presidential Debate of the 2024 General Election Between Vice President Kamala Harris and Former President Donald Trump, Part 3",
            "Score": 2561,
            "URL": "https://www.reddit.com/r/politics/comments/1fdypmd/discussion_thread_first_presidential_debate_of/",
            "Created_UTC": 1726018918.0
        },
        {
            "Title": "\u2018Trump is going to be cross-examined\u2019: US prepares for presidential debate",
            "Score": 3232,
            "URL": "https://www.theguardian.com/us-news/article/2024/sep/08/kamala-harris-trump-presidential-debate",
            "Created_UTC": 1725791929.0
        },
        {
            "Title": "Discussion Thread: First Presidential Debate of the 2024 General Election Between Vice President Kamala Harris and Former President Donald Trump, Part 4",
            "Score": 1512,
            "URL": "https://www.reddit.com/r/politics/comments/1fdyytn/discussion_thread_first_presidential_debate_of/",
            "Created_UTC": 1726019757.0
        },
        {
            "Title": "What to Expect in the Trump-Harris Presidential Debate and How to Watch It",
            "Score": 26,
            "URL": "https://www.wired.com/story/what-to-expect-trump-harris-presidential-debate-how-to-watch/",
            "Created_UTC": 1725901573.0
        },
        {
            "Title": "Trump and Harris' first presidential debate of 2024 is tomorrow. Where to stream it, what the rules will be.",
            "Score": 281,
            "URL": "https://www.cbsnews.com/news/trump-harris-2024-first-debate-what-to-know/",
            "Created_UTC": 1725883955.0
        },
        {
            "Title": "10 Tough Climate Questions for the Presidential Debate\nClimate and energy get little acknowledgement in most political debates. But there are plenty of questions for both Trump and Harris on the urgent choices the next president faces.",
            "Score": 37,
            "URL": "https://insideclimatenews.org/news/09092024/10-tough-climate-questions-for-the-presidential-debate/",
            "Created_UTC": 1725892065.0
        },
        {
            "Title": "In debate, Trump rants, cites conspiracy theories as Harris pushes back, touts her vision for future",
            "Score": 175,
            "URL": "https://www.upi.com/Top_News/US/2024/09/10/Philadelphia-Kamala-Harris-Donald-Trump-Pennsylvania-presidential-debate/9851725997307/",
            "Created_UTC": 1726052244.0
        },
        {
            "Title": "Discussion Thread: 2024 Delaware, New Hampshire, and Rhode Island Primaries",
            "Score": 53,
            "URL": "https://www.reddit.com/r/politics/comments/1fdjpet/discussion_thread_2024_delaware_new_hampshire_and/",
            "Created_UTC": 1725979736.0
        },
        {
            "Title": "Donald Trump threatens to pull out of 10 September presidential debate",
            "Score": 676,
            "URL": "https://www.theguardian.com/us-news/article/2024/aug/26/trump-harris-presidential-debate?CMP=Share_AndroidApp_Other",
            "Created_UTC": 1724678963.0
        },
        {
            "Title": "Donald Trump threatens to pull out of 10 September presidential debate",
            "Score": 228,
            "URL": "https://www.theguardian.com/us-news/article/2024/aug/26/trump-harris-presidential-debate",
            "Created_UTC": 1724678685.0
        },
        {
            "Title": "The first presidential debate was the most consequential in history. The next one has similar stakes.",
            "Score": 43,
            "URL": "https://www.bostonglobe.com/2024/08/27/nation/harris-trump-debate-presidential-momentum/https://www.bostonglobe.com/2024/08/27/nation/harris-trump-debate-presidential-momentum/?s_campaign=audience:reddit",
            "Created_UTC": 1724768195.0
        },
        {
            "Title": "Vance, Walz agree to Oct. 1 vice-presidential debate ",
            "Score": 140,
            "URL": "https://www.washingtonpost.com/politics/2024/08/15/vance-walz-debate-cbs/?utm_campaign=wp_main&utm_medium=social&utm_source=reddit.com",
            "Created_UTC": 1723731152.0
        },
        {
            "Title": "Walz to grill Vance on Project 2025 in first vice-presidential debate",
            "Score": 622,
            "URL": "https://www.theguardian.com/us-news/article/2024/aug/15/vp-debate-walz-vance-project-2025",
            "Created_UTC": 1723775269.0
        },
        {
            "Title": "JD Vance agrees to October vice-presidential debate with Tim Walz",
            "Score": 151,
            "URL": "https://www.theguardian.com/us-news/article/2024/aug/15/vance-walz-vp-debate",
            "Created_UTC": 1723752731.0
        },
        {
            "Title": "Vance and Walz agree to a vice presidential debate on Oct. 1 hosted by CBS News",
            "Score": 116,
            "URL": "https://apnews.com/article/60650c0480e132342880c35a1d29f539",
            "Created_UTC": 1723730047.0
        },
        {
            "Title": "ABC says Trump and Harris have agreed to participate in a presidential debate on Sept. 10",
            "Score": 8776,
            "URL": "https://apnews.com/article/94b590ddf0434d9ea7b1241396dbbcc6",
            "Created_UTC": 1723144029.0
        },
        {
            "Title": "Trump and Harris have agreed to a Sept. 10 presidential debate on ABC, network says",
            "Score": 699,
            "URL": "https://www.pbs.org/newshour/politics/trump-and-harris-have-agreed-to-a-sept-10-presidential-debate-on-abc-network-says",
            "Created_UTC": 1723147623.0
        },
        {
            "Title": "Second presidential debate requirements are released: Will Harris and Trump face off?",
            "Score": 97,
            "URL": "https://www.usatoday.com/story/news/politics/elections/2024/07/26/second-presidential-debate-requirements-released-trump-harris/74563640007/",
            "Created_UTC": 1722790126.0
        },
        {
            "Title": "Trump says Biden wasn't 'too old' to be president",
            "Score": 29457,
            "URL": "https://www.newsweek.com/trump-says-biden-wasnt-too-old-president-1932987",
            "Created_UTC": 1722516611.0
        },
        {
            "Title": "Harris mocks Trump after he hedges (again) on presidential debate | \nThe more Donald Trump hedges on debating the likely Democratic nominee, the more eager Kamala Harris is to mock the former Republican president.",
            "Score": 1105,
            "URL": "https://www.msnbc.com/rachel-maddow-show/maddowblog/kamala-harris-mocks-donald-trump-election-presidential-debate-2024-rcna163777",
            "Created_UTC": 1722064922.0
        },
        {
            "Title": "Donald Trump Doubles Down On Plans To Dodge Next Presidential Debate",
            "Score": 29413,
            "URL": "https://www.huffpost.com/entry/donald-trump-debate-abc-news-kamala-harris_n_669f4f46e4b008fc7de1d957",
            "Created_UTC": 1721733882.0
        },
        {
            "Title": "With Biden out of the race, what's next for the upcoming presidential debate?",
            "Score": 72,
            "URL": "https://www.usatoday.com/story/news/politics/elections/2024/07/22/trump-harris-next-presidential-debate/74495549007/",
            "Created_UTC": 1721662484.0
        },
        {
            "Title": "Megathread: President Biden Announces That He Will Not Seek Reelection",
            "Score": 56062,
            "URL": "https://www.reddit.com/r/politics/comments/1e8sabh/megathread_president_biden_announces_that_he_will/",
            "Created_UTC": 1721584791.0
        },
        {
            "Title": "Megathread: President Biden Announces That He Will Not Seek Reelection, Endorses VP Harris",
            "Score": 19186,
            "URL": "https://www.reddit.com/r/politics/comments/1e8twp4/megathread_president_biden_announces_that_he_will/",
            "Created_UTC": 1721588881.0
        },
        {
            "Title": "Biden Narrows Gap With Trump in Swing States Despite Debate Loss | Biden has narrowed Trump\u2019s lead in swing states despite a widely panned presidential debate performance, the Bloomberg News/Morning Consult poll finds",
            "Score": 2374,
            "URL": "https://www.bloomberg.com/news/features/2024-07-06/biden-narrows-trump-s-election-lead-in-key-states-after-debate-poll",
            "Created_UTC": 1720270880.0
        },
        {
            "Title": "Biden says 'no one is pushing me out' of presidential race after disastrous debate",
            "Score": 1391,
            "URL": "https://www.pbs.org/newshour/politics/biden-says-no-one-is-pushing-me-out-of-presidential-race-after-disastrous-debate",
            "Created_UTC": 1720031567.0
        },
        {
            "Title": "Discussion Thread: President Biden Gives Press Conference at NATO Summit",
            "Score": 5947,
            "URL": "https://www.reddit.com/r/politics/comments/1e0zgq5/discussion_thread_president_biden_gives_press/",
            "Created_UTC": 1720731325.0
        },
        {
            "Title": "Fact checking the CNN presidential debate",
            "Score": 60,
            "URL": "https://www.cnn.com/2024/06/27/politics/fact-checking-the-cnn-presidential-debate/index.html",
            "Created_UTC": 1719546011.0
        },
        {
            "Title": "Melania Trump missing as Jill Biden attends presidential debate",
            "Score": 616,
            "URL": "https://www.newsweek.com/melania-trump-missing-jill-biden-attends-presidential-debate-1918531",
            "Created_UTC": 1719587585.0
        },
        {
            "Title": "Historian who predicted 9 of the last 10 election results says Democrats shouldn't drop Joe Biden",
            "Score": 2348,
            "URL": "https://www.usatoday.com/story/news/politics/elections/2024/06/30/lichtman-dems-replace-biden/74260967007/",
            "Created_UTC": 1720213258.0
        },
        {
            "Title": "Ratings for first presidential debate down sharply from 2020",
            "Score": 57,
            "URL": "https://www.washingtonpost.com/style/media/2024/06/28/2024-debate-ratings-biden-trump/",
            "Created_UTC": 1719602531.0
        },
        {
            "Title": "When the next presidential debate of 2024 takes place and who will moderate it",
            "Score": 73,
            "URL": "https://www.cbsnews.com/news/when-is-second-presidential-debate-2024/",
            "Created_UTC": 1719715231.0
        },
        {
            "Title": "Discussion Thread: First US Presidential General Election Debate of 2024 Between Joe Biden and Donald Trump, Post-Debate Discussion",
            "Score": 3449,
            "URL": "https://www.reddit.com/r/politics/comments/1dq932e/discussion_thread_first_us_presidential_general/",
            "Created_UTC": 1719542361.0
        },
        {
            "Title": "Discussion Thread: President Biden Gives First Post-Debate Interview",
            "Score": 6410,
            "URL": "https://www.reddit.com/r/politics/comments/1dwauiu/discussion_thread_president_biden_gives_first/",
            "Created_UTC": 1720219863.0
        },
        {
            "Title": "Inside CNN's Presidential Debate: How it will work",
            "Score": 13,
            "URL": "https://www.cnn.com/2024/06/26/politics/video/cnn-presidential-debate-2024-biden-trump-mattingly-blackwell-digvid",
            "Created_UTC": 1719518583.0
        },
        {
            "Title": "2024 presidential debates: Voters' preferences for topics and format [OC]",
            "Score": 25,
            "URL": "https://today.yougov.com/politics/articles/49820-presidential-debates-voters-preferences-for-topics-format",
            "Created_UTC": 1719334736.0
        },
        {
            "Title": "Fact-checking Joe Biden and Donald Trump\u2019s first 2024 presidential debate",
            "Score": 546,
            "URL": "https://www.politifact.com/article/2024/jun/27/2024-presidential-debate-live-fact-check/",
            "Created_UTC": 1719541300.0
        }
    ]
}